odoo10_addon_web_widget_bokeh_chart-10.0.1.0.0-py2.7-nspkg.pth
odoo/addons/web_widget_bokeh_chart/README.rst
odoo/addons/web_widget_bokeh_chart/__init__.py
odoo/addons/web_widget_bokeh_chart/__manifest__.py
odoo/addons/web_widget_bokeh_chart/static/description/example.png
odoo/addons/web_widget_bokeh_chart/static/description/icon.png
odoo/addons/web_widget_bokeh_chart/static/src/js/web_widget_bokeh_chart.js
odoo/addons/web_widget_bokeh_chart/static/src/lib/bokeh/bokeh-0.12.7.css
odoo/addons/web_widget_bokeh_chart/static/src/lib/bokeh/bokeh-0.12.7.js
odoo/addons/web_widget_bokeh_chart/static/src/lib/bokeh/bokeh-widgets-0.12.7.css
odoo/addons/web_widget_bokeh_chart/static/src/lib/bokeh/bokeh-widgets-0.12.7.js
odoo/addons/web_widget_bokeh_chart/views/web_widget_bokeh_chart.xml
odoo10_addon_web_widget_bokeh_chart-10.0.1.0.0.dist-info/DESCRIPTION.rst
odoo10_addon_web_widget_bokeh_chart-10.0.1.0.0.dist-info/METADATA
odoo10_addon_web_widget_bokeh_chart-10.0.1.0.0.dist-info/RECORD
odoo10_addon_web_widget_bokeh_chart-10.0.1.0.0.dist-info/WHEEL
odoo10_addon_web_widget_bokeh_chart-10.0.1.0.0.dist-info/metadata.json
odoo10_addon_web_widget_bokeh_chart-10.0.1.0.0.dist-info/namespace_packages.txt
odoo10_addon_web_widget_bokeh_chart-10.0.1.0.0.dist-info/top_level.txt
